{
	"Changes": [
		{
			"LogName": "Question Dialogue",
			"Action": "EditData",
			"Target": "Characters/Dialogue/MichaelHart",
			"Entries": {
				"Introduction": "{{i18n:Michael_Introduction}}",
				"ESIntroduction": "$1 MichaelHart_Introduction#{{i18n:Michael_ESIntroduction}}#$e#{{i18n:Michael_Mon}}",
				"HartResidence_2_35": "{{i18n:Michael_HartResidence_2_35}}",
				"Resort":"{{i18n:Michael_Resort}}",
				"cc_Complete": "{{i18n:Michael_cc_Complete}}",
				"spring_12": "{{i18n:Michael_spring_12}}",
				"spring_27": "{{i18n:Michael_spring_27}}",
				"spring_27_2": "{{i18n:Michael_spring_27_2}}",
				"summer_1": "{{i18n:Michael_summer_1}}",
				"summer_1_2": "{{i18n:Michael_summer_1_2}}",
				"summer_28": "{{i18n:Michael_summer_28}}",
				"fall_28": "{{i18n:Michael_fall_28}}",
				"winter_1": "{{i18n:Michael_winter_1}}",
				"Mon": "{{i18n:Michael_Mon}}",
				"Mon6": "{{i18n:Michael_Mon6}}",
				"winter_Mon6": "{{i18n:Michael_winter_Mon6}}",
				"Mon8": "{{i18n:Michael_Mon8}}",
				"summer_Mon": "{{i18n:Michael_summer_Mon}}",
				"Tue": "{{i18n:Michael_Tue}}",
				"summer_Tue2": "{{i18n:Michael_summer_Tue2}}",
				"fall_Tue4": "{{i18n:Michael_fall_Tue4}}",
				"Tue6": "{{i18n:Michael_Tue6}}",
				"summer_Tue": "{{i18n:Michael_summer_Tue}}",
				"summer_Tue6": "{{i18n:Michael_summer_Tue6}}",
				"Wed": "{{i18n:Michael_Wed}}",
				"Wed6": "{{i18n:Michael_Wed6}}",
				"fall_Wed4": "{{i18n:Michael_fall_Wed4}}",
				"winter_Wed4": "{{i18n:Michael_winter_Wed4}}",
				"summer_Wed": "{{i18n:Michael_summer_Wed}}",
				"summer_Wed6": "{{i18n:Michael_summer_Wed6}}",
				"Thu": "{{i18n:Michael_Thu}}",
				"Thu4": "{{i18n:Michael_Thu4}}",
				"Thu6": "{{i18n:Michael_Thu6}}",
				"fall_Thu6": "{{i18n:Michael_fall_Thu6}}",
				"spring_Thu8": "{{i18n:Michael_spring_Thu8}}",
				"winter_Thu8": "{{i18n:Michael_winter_Thu8}}",
				"summer_Thu": "{{i18n:Michael_summer_Thu}}",
				"summer_Thu6": "{{i18n:Michael_summer_Thu6}}",
				"Fri": "{{i18n:Michael_Fri}}",
				"Fri4": "{{i18n:Michael_Fri4}}",
				"fall_Fri6": "{{i18n:Michael_fall_Fri6}}",
				"winter_Fri8": "{{i18n:Michael_winter_Fri8}}",
				"summer_Fri": "{{i18n:Michael_summer_Fri}}[(O)EastScarp_PheasantEgg_male (O)EastScarp_PheasantEgg_female]",
				"summer_Fri6": "{{i18n:Michael_summer_Fri6}}",
				"Sat": "{{i18n:Michael_Sat}}",
				"Sat6": "{{i18n:Michael_Sat6}}",
				"spring_Sat6": "{{i18n:Michael_spring_Sat6}}",
				"fall_Sat6": "{{i18n:Michael_fall_Sat6}}",
				"summer_Sat": "{{i18n:Michael_summer_Sat}}",
				"spring_Sat10": "{{i18n:Michael_spring_Sat10}}",
				"Sun": "{{i18n:Michael_Sun}}",
				"Sun2": "{{i18n:Michael_Sun2}}",
				"Sun8": "{{i18n:Michael_Sun8}}",
				"fall_Sun6": "{{i18n:Michael_fall_Sun6}}",
				"winter_Sun6": "{{i18n:Michael_winter_Sun6}}",
				"summer_Sun": "{{i18n:Michael_summer_Sun}}",
				"AcceptGift_(O)EastScarp_SeaGlass": "{{i18n:Michael_AcceptGift_(O)EastScarp_SeaGlass}}",
				"EthanBackToSchool":"{{i18n:Michael_EthanBackToSchool}}"
			}
		},
		{
			"LogName": "Question Dialogue",
			"Action": "EditData",
			"Target": "Strings/schedules/MichaelHart",
			"Entries": {
				"winter_15.000": "{{i18n:Strings.MichaelHart.winter_15.000}}",
				"winter_16.000": "{{i18n:Strings.MichaelHart.winter_16.000}}",
				"winter_17.000": "{{i18n:Strings.MichaelHart.winter_17.000}}",
				"Wed.000": "{{i18n:Strings.MichaelHart.Wed.000}}",
				"Thu.000a": "{{i18n:Strings.MichaelHart.Thu.000a}}",
				"Thu.000b": "{{i18n:Strings.MichaelHart.Thu.000b}}",
				"Thu.000c": "{{i18n:Strings.MichaelHart.Thu.000c}}",
				"Fri.000.spring": "{{i18n:Strings.MichaelHart.Fri.000.spring}}",
				"Fri.000.summer": "{{i18n:Strings.MichaelHart.Fri.000.summer}}",
				"Fri.000.fall": "{{i18n:Strings.MichaelHart.Fri.000.fall}}",
				"Fri.000.winter": "{{i18n:Strings.MichaelHart.Fri.000.winter}}",
			}
		}
	]
}